LICENSE
MANIFEST.in
README.md
requirements.txt
setup.cfg
setup.py
gcdt_bundler/__init__.py
gcdt_bundler/bundler.py
gcdt_bundler/bundler_utils.py
gcdt_bundler/python_bundler.py
gcdt_bundler.egg-info/PKG-INFO
gcdt_bundler.egg-info/SOURCES.txt
gcdt_bundler.egg-info/dependency_links.txt
gcdt_bundler.egg-info/entry_points.txt
gcdt_bundler.egg-info/requires.txt
gcdt_bundler.egg-info/top_level.txt
gcdt_bundler/vendor/__init__.py
gcdt_bundler/vendor/nodeenv.py